stears_client/__init__.py
stears_client/client.py
stears_client-0.1.1.dist-info/METADATA
stears_client-0.1.1.dist-info/WHEEL
stears_client-0.1.1.dist-info/RECORD
