Metadata-Version: 2.1
Name: stears-client
Version: 0.1.1
Summary: A python client for Radiant AI's Stears Project API
Home-page: https://getradiant.ai
Author: localminimum
Author-email: min@getradiant.ai
Requires-Python: >=3.13,<4.0
Classifier: Operating System :: OS Independent
Classifier: Programming Language :: Python :: 3
Classifier: Programming Language :: Python :: 3.13
Requires-Dist: aiohttp (>=3.12.13,<4.0.0)
Requires-Dist: dotenv (>=0.9.9,<0.10.0)
Requires-Dist: requests (>=2.32.4,<3.0.0)
